{
  "id": "20260518_160754_5092",
  "source": "feishu_nora",
  "bot": "nora",
  "input": "还有@_user_1 域名注册了吗？",
  "input_preview": "还有@_user_1 域名注册了吗？",
  "output": "Chloe，关于域名注册的事儿，我已经和 Sage 碰过了，下面跟你同步一下。\n\n这件事其实分两步走：**先查再注册**，但需要你先拍板几个关键信息。\n\n---\n\n### 🌐 第一步：确认咱们的目标和信息\n\nSage 可以写个小工具，一键查域名、一键注册，全程自动跑。但跑之前，你得先告诉我：\n\n1. **你想注册的完整域名**  \n   比如 `sue-tech.com`，或者你之前提过的某个名字。\n\n2. **咱们准备用哪家注册商**  \n   常见的比如 Namecheap、GoDaddy、阿里云。如果公司已经有账号，告诉我平台名字就行；如果还没选，我推荐 Namecheap，对技术团队友好。\n\n3. **账号的 API 密钥**（如果已有）  \n   听起来有点技术，其实就是注册商给的一串“钥匙”，让程序能替你去操作。找不到的话，我们可以改成手动注册或者我教你从后台拿。\n\n4. **注册用的联系人信息**  \n   注册域名时 WHOIS 要填的信息：姓名、公司名（Sue Tech）、地址、邮箱、电话等。\n\n> 🔒 法律提示：域名属于公司无形资产，建议用公司名义注册，联系人信息留 Chloe 或授权人。涉及重大决策可再咨询律师。我只是参考意见。\n\n---\n\n### ⚙️ 第二步：我安排 Sage 操作\n\n你给到上面信息后，我的分工是：\n\n- **Sage**：立即用脚本查域名状态 → 若未注册，自动完成注册并反馈结果。\n- **Elle**：暂不涉及，后续补充商标相关建议时再请她介入。\n\n整个过程你不需要碰代码，Sage 会把工具包好，我给你翻译每一步在干啥。\n\n---\n\n**下一步行动**：你先把目标域名和注册商告诉我，哪怕只是几个备选名字也行，我让 Sage 先把“查状态”跑起来。查完了我们再定注册。",
  "output_preview": "Chloe，关于域名注册的事儿，我已经和 Sage 碰过了，下面跟你同步一下。\n\n这件事其实分两步走：**先查再注册**，但需要你先拍板几个关键信息。\n\n---\n\n### 🌐 第一步：确认咱们的目标和信息\n\nSage 可以写个小工具，一键查域名、一键注册，全程自动跑。但跑之前，你得先告诉我：\n\n1. **你想注册的完整域名**  \n   比如 `sue-tech.com`，或者你之前提过的某个名字",
  "timestamp": "2026-05-18T16:07:54.509252+08:00",
  "elapsed_seconds": 98.09,
  "agents": [
    "nora",
    "sage",
    "elle"
  ],
  "status": "done"
}